site_map_parser-0.3.9.data/scripts/smapper
sitemapparser/__init__.py
sitemapparser/base_data.py
sitemapparser/data_helpers.py
sitemapparser/exporter.py
sitemapparser/logging_config.ini
sitemapparser/site_map_parser.py
sitemapparser/sitemap.py
sitemapparser/sitemap_index.py
sitemapparser/smapper_utils.py
sitemapparser/url.py
sitemapparser/url_set.py
sitemapparser/exporters/__init__.py
sitemapparser/exporters/csv_exporter.py
sitemapparser/exporters/json_exporter.py
site_map_parser-0.3.9.dist-info/LICENSE
site_map_parser-0.3.9.dist-info/METADATA
site_map_parser-0.3.9.dist-info/WHEEL
site_map_parser-0.3.9.dist-info/top_level.txt
site_map_parser-0.3.9.dist-info/RECORD
