Metadata-Version: 2.1
Name: site-map-parser
Version: 0.3.9
Summary: Script/Library to read and parse sitemap.xml data
Home-page: https://github.com/daveoconnor/site-map-parser
Author: Dave O'Connor
Author-email: github@dead-pixels.org
License: UNKNOWN
Platform: UNKNOWN
Classifier: Programming Language :: Python :: 3
Classifier: Programming Language :: Python :: 3.6
Classifier: Programming Language :: Python :: 3.7
Classifier: Programming Language :: Python :: 3.8
Classifier: Programming Language :: Python :: 3.9
Classifier: Programming Language :: Python :: 3.10
Classifier: License :: OSI Approved :: MIT License
Classifier: Operating System :: OS Independent
Requires-Python: >=3.6
Requires-Dist: lxml
Requires-Dist: requests
Requires-Dist: python-dateutil
